{"_start": {"/test/bc_gt/612-C-bug-15186001-15186009/bugcode/612-C-15186001": ["31", "ed", "49", "89", "d1", "5e", "48", "89", "e2", "48", "83", "e4", "f0", "50", "54", "49", "c7", "c0", "a0", "09", "40", "00", "48", "c7", "c1", "30", "09", "40", "00", "48", "c7", "c7", "e3", "06", "40", "00", "e8", "a7", "ff", "ff", "ff", "f4", "66", "0f", "1f", "44", "00", "00"]}, "deregister_tm_clones": {"/test/bc_gt/612-C-bug-15186001-15186009/bugcode/612-C-15186001": ["b8", "5f", "10", "60", "00", "55", "48", "2d", "58", "10", "60", "00", "48", "83", "f8", "0e", "48", "89", "e5", "76", "1b", "b8", "00", "00", "00", "00", "48", "85", "c0", "74", "11", "5d", "bf", "58", "10", "60", "00", "ff", "e0", "66", "0f", "1f", "84", "00", "00", "00", "00", "00", "5d", "c3", "0f", "1f", "40", "00", "66", "2e", "0f", "1f", "84", "00", "00", "00", "00", "00"]}, "register_tm_clones": {"/test/bc_gt/612-C-bug-15186001-15186009/bugcode/612-C-15186001": ["be", "58", "10", "60", "00", "55", "48", "81", "ee", "58", "10", "60", "00", "48", "c1", "fe", "03", "48", "89", "e5", "48", "89", "f0", "48", "c1", "e8", "3f", "48", "01", "c6", "48", "d1", "fe", "74", "15", "b8", "00", "00", "00", "00", "48", "85", "c0", "74", "0b", "5d", "bf", "58", "10", "60", "00", "ff", "e0", "0f", "1f", "00", "5d", "c3", "66", "0f", "1f", "44", "00", "00"]}, "__do_global_dtors_aux": {"/test/bc_gt/612-C-bug-15186001-15186009/bugcode/612-C-15186001": ["80", "3d", "31", "0a", "20", "00", "00", "75", "11", "55", "48", "89", "e5", "e8", "6e", "ff", "ff", "ff", "5d", "c6", "05", "1e", "0a", "20", "00", "01", "f3", "c3", "0f", "1f", "40", "00"]}, "frame_dummy": {"/test/bc_gt/612-C-bug-15186001-15186009/bugcode/612-C-15186001": ["bf", "20", "0e", "60", "00", "48", "83", "3f", "00", "75", "05", "eb", "93", "0f", "1f", "00", "b8", "00", "00", "00", "00", "48", "85", "c0", "74", "f1", "55", "48", "89", "e5", "ff", "d0", "5d", "e9", "7a", "ff", "ff", "ff"]}, "_Z6isPaircc": {"/test/bc_gt/612-C-bug-15186001-15186009/bugcode/612-C-15186001": ["55", "48", "89", "e5", "89", "fa", "89", "f0", "88", "55", "fc", "88", "45", "f8", "80", "7d", "fc", "3c", "75", "14", "80", "7d", "f8", "3e", "75", "07", "b8", "01", "00", "00", "00", "eb", "5a", "b8", "00", "00", "00", "00", "eb", "53", "80", "7d", "fc", "7b", "75", "14", "80", "7d", "f8", "7d", "75", "07", "b8", "01", "00", "00", "00", "eb", "40", "b8", "00", "00", "00", "00", "eb", "39", "80", "7d", "fc", "5b", "75", "14", "80", "7d", "f8", "5d", "75", "07", "b8", "01", "00", "00", "00", "eb", "26", "b8", "00", "00", "00", "00", "eb", "1f", "80", "7d", "fc", "28", "75", "14", "80", "7d", "f8", "29", "75", "07", "b8", "01", "00", "00", "00", "eb", "0c", "b8", "00", "00", "00", "00", "eb", "05", "b8", "00", "00", "00", "00", "5d", "c3"]}, "main": {"/test/bc_gt/612-C-bug-15186001-15186009/bugcode/612-C-15186001": ["55", "48", "89", "e5", "41", "57", "41", "56", "41", "55", "41", "54", "53", "48", "81", "ec", "98", "42", "0f", "00", "89", "bd", "4c", "bd", "f0", "ff", "48", "89", "b5", "40", "bd", "f0", "ff", "64", "48", "8b", "04", "25", "28", "00", "00", "00", "48", "89", "45", "c8", "31", "c0", "48", "89", "e0", "48", "89", "c3", "48", "8d", "85", "80", "bd", "f0", "ff", "48", "89", "c6", "bf", "b4", "09", "40", "00", "b8", "00", "00", "00", "00", "e8", "1e", "fe", "ff", "ff", "48", "8d", "85", "80", "bd", "f0", "ff", "48", "89", "c7", "e8", "cf", "fd", "ff", "ff", "89", "85", "6c", "bd", "f0", "ff", "8b", "85", "6c", "bd", "f0", "ff", "48", "98", "48", "83", "e8", "01", "48", "89", "85", "70", "bd", "f0", "ff", "48", "89", "c2", "48", "83", "c2", "01", "49", "89", "d6", "41", "bf", "00", "00", "00", "00", "48", "89", "c2", "48", "83", "c2", "01", "49", "89", "d4", "41", "bd", "00", "00", "00", "00", "48", "8d", "50", "01", "b8", "10", "00", "00", "00", "48", "83", "e8", "01", "48", "01", "d0", "b9", "10", "00", "00", "00", "ba", "00", "00", "00", "00", "48", "f7", "f1", "48", "6b", "c0", "10", "48", "29", "c4", "48", "89", "e0", "48", "83", "c0", "00", "48", "89", "85", "78", "bd", "f0", "ff", "c7", "85", "64", "bd", "f0", "ff", "00", "00", "00", "00", "c7", "85", "68", "bd", "f0", "ff", "00", "00", "00", "00", "c7", "85", "60", "bd", "f0", "ff", "00", "00", "00", "00", "8b", "85", "60", "bd", "f0", "ff", "3b", "85", "6c", "bd", "f0", "ff", "0f", "8d", "ef", "00", "00", "00", "8b", "85", "60", "bd", "f0", "ff", "48", "98", "0f", "b6", "84", "05", "80", "bd", "f0", "ff", "3c", "3c", "74", "3c", "8b", "85", "60", "bd", "f0", "ff", "48", "98", "0f", "b6", "84", "05", "80", "bd", "f0", "ff", "3c", "7b", "74", "28", "8b", "85", "60", "bd", "f0", "ff", "48", "98", "0f", "b6", "84", "05", "80", "bd", "f0", "ff", "3c", "5b", "74", "14", "8b", "85", "60", "bd", "f0", "ff", "48", "98", "0f", "b6", "84", "05", "80", "bd", "f0", "ff", "3c", "28", "75", "2b", "8b", "85", "60", "bd", "f0", "ff", "48", "98", "0f", "b6", "8c", "05", "80", "bd", "f0", "ff", "48", "8b", "95", "78", "bd", "f0", "ff", "8b", "85", "68", "bd", "f0", "ff", "48", "98", "88", "0c", "02", "83", "85", "68", "bd", "f0", "ff", "01", "eb", "68", "83", "bd", "68", "bd", "f0", "ff", "00", "74", "53", "83", "ad", "68", "bd", "f0", "ff", "01", "48", "8b", "95", "78", "bd", "f0", "ff", "8b", "85", "68", "bd", "f0", "ff", "48", "98", "0f", "b6", "04", "02", "88", "85", "5f", "bd", "f0", "ff", "8b", "85", "60", "bd", "f0", "ff", "48", "98", "0f", "b6", "84", "05", "80", "bd", "f0", "ff", "0f", "be", "d0", "0f", "be", "85", "5f", "bd", "f0", "ff", "89", "d6", "89", "c7", "e8", "c3", "fd", "ff", "ff", "83", "f0", "01", "84", "c0", "74", "15", "83", "85", "64", "bd", "f0", "ff", "01", "eb", "0c", "bf", "b7", "09", "40", "00", "e8", "43", "fc", "ff", "ff", "eb", "0c", "83", "85", "60", "bd", "f0", "ff", "01", "e9", "ff", "fe", "ff", "ff", "83", "bd", "68", "bd", "f0", "ff", "00", "74", "0c", "bf", "b7", "09", "40", "00", "e8", "22", "fc", "ff", "ff", "eb", "17", "8b", "85", "64", "bd", "f0", "ff", "89", "c6", "bf", "c2", "09", "40", "00", "b8", "00", "00", "00", "00", "e8", "39", "fc", "ff", "ff", "b8", "00", "00", "00", "00", "48", "89", "dc", "48", "8b", "4d", "c8", "64", "48", "33", "0c", "25", "28", "00", "00", "00", "74", "05", "e8", "0d", "fc", "ff", "ff", "48", "8d", "65", "d8", "5b", "41", "5c", "41", "5d", "41", "5e", "41", "5f", "5d", "c3", "66", "2e", "0f", "1f", "84", "00", "00", "00", "00", "00", "0f", "1f", "40", "00"]}, "__libc_csu_init": {"/test/bc_gt/612-C-bug-15186001-15186009/bugcode/612-C-15186001": ["41", "57", "41", "56", "41", "89", "ff", "41", "55", "41", "54", "4c", "8d", "25", "ce", "04", "20", "00", "55", "48", "8d", "2d", "ce", "04", "20", "00", "53", "49", "89", "f6", "49", "89", "d5", "4c", "29", "e5", "48", "83", "ec", "08", "48", "c1", "fd", "03", "e8", "6f", "fb", "ff", "ff", "48", "85", "ed", "74", "20", "31", "db", "0f", "1f", "84", "00", "00", "00", "00", "00", "4c", "89", "ea", "4c", "89", "f6", "44", "89", "ff", "41", "ff", "14", "dc", "48", "83", "c3", "01", "48", "39", "eb", "75", "ea", "48", "83", "c4", "08", "5b", "5d", "41", "5c", "41", "5d", "41", "5e", "41", "5f", "c3", "90", "66", "2e", "0f", "1f", "84", "00", "00", "00", "00", "00"]}, "__libc_csu_fini": {"/test/bc_gt/612-C-bug-15186001-15186009/bugcode/612-C-15186001": ["f3", "c3"]}}